{
  "namespace": ["discord", "emoji"],
  "comment": "\nhttps://discord.com/developers/docs/resources/emoji#emoji-object-emoji-structure",
  "defs":
  [
    {
      "struct":"dati",
      "fields":
      [
        { "name": "id", "type":{ "base":"char", "dec":"*", "converter":"snowflake"}},
        { "name": "name", "type":{ "base":"char", "dec":"[MAX_NAME_LEN]"}},
        { "name": "roles", "todo":true },
        { "name": "user", "type":{ "base":"discord::user::dati", "dec":"*" }},
        { "name": "require_colons", "type":{ "base":"bool" }},
        { "name": "managed", "type":{ "base":"bool" }},
        { "name": "animated", "type":{ "base":"bool" }},
        { "name": "available", "type":{ "base":"bool" }},
      ]
    }
  ]
}
