{
    "namespace": ["discord", "Template"],
    "comment": " xxx ",
    "structs":
    [
	{
	    "name":"dati",
	    "fields":
	    [
		{ "name": "code", "type":{ "base":"char", "dec":"*" }},
		{ "name": "name", "type":{ "base":"char", "dec":"*" }},
		{ "name": "description", "type":{ "base":"char", "dec":"*" }},
		{ "name": "usage_count", "type":{ "base":"int" }},
		{ "name": "creator_id", "type":{ "base":"uint64_t" }},
		{ "name": "creator", "type":{ "base":"user::dati", "dec":"*" }},
		{ "name": "created_at", "type":{ "base":"uint64_t" }},
		{ "name": "updated_at", "type":{ "base":"uint64_t" }},
		{ "name": "source_guild_id", "type":{ "base":"uint64_t" }},
		{ "name": "serialized_source_guild", "type":{ "base":"guild::dati", "dec":"*" }},
		{ "name": "is_dirty", "type":{ "base":"bool" }},
	    ]
	}
    ]
}
